{
  "counter" : {
    "primary" : 3888,
    "tertiary" : 0,
    "tertiaryMax" : 400
  },
  "registerTables" : [ {
    "id" : "1dadd316-5ca4-4704-a13f-18f22f991f18",
    "tableNumber" : 11,
    "tableName" : "1",
    "difficulty" : "Normal",
    "players" : 1,
    "playersInfo" : [ {
      "character" : "Spiderman (Peter Parker)",
      "aspect" : "Protección"
    } ],
    "code" : "C9B0C2",
    "createdAt" : 1770977041.576614100,
    "avatar" : "3"
  } ],
  "freeGameTables" : [ ],
  "mesaTotals" : { },
  "mesaEvents" : [ ],
  "sectorStates" : {
    "11" : {
      "mesaId" : 11,
      "mangog" : {
        "key" : "mangog",
        "activeMesaId" : null,
        "value" : 0,
        "defeated" : false
      },
      "gate" : {
        "key" : "gate",
        "activeMesaId" : null,
        "value" : 0,
        "defeated" : false
      }
    },
    "12" : {
      "mesaId" : 12,
      "mangog" : {
        "key" : "mangog",
        "activeMesaId" : null,
        "value" : 0,
        "defeated" : false
      },
      "gate" : {
        "key" : "gate",
        "activeMesaId" : null,
        "value" : 0,
        "defeated" : false
      }
    },
    "44" : {
      "mesaId" : 44,
      "mangog" : {
        "key" : "mangog",
        "activeMesaId" : null,
        "value" : 0,
        "defeated" : false
      },
      "gate" : {
        "key" : "gate",
        "activeMesaId" : null,
        "value" : 0,
        "defeated" : false
      }
    }
  },
  "qrEventEnabled" : false,
  "qrFreegameEnabled" : false,
  "ts" : 1770989318633
}